{
  "main": {
    "id": "ec47ff1863f9e345",
    "type": "split",
    "children": [
      {
        "id": "e331434870a83be0",
        "type": "tabs",
        "children": [
          {
            "id": "735318b20f393cbb",
            "type": "leaf",
            "state": {
              "type": "markdown",
              "state": {
                "file": "Installation.md",
                "mode": "preview",
                "source": false
              },
              "icon": "lucide-file",
              "title": "Installation"
            }
          }
        ]
      }
    ],
    "direction": "vertical"
  },
  "left": {
    "id": "270b9944d5f84493",
    "type": "split",
    "children": [
      {
        "id": "bddd69539ec8f11d",
        "type": "tabs",
        "children": [
          {
            "id": "b684573afe216b4b",
            "type": "leaf",
            "state": {
              "type": "file-explorer",
              "state": {
                "sortOrder": "alphabetical",
                "autoReveal": false
              },
              "icon": "lucide-folder-closed",
              "title": "Files"
            }
          },
          {
            "id": "ad5b15a9bae81c09",
            "type": "leaf",
            "state": {
              "type": "search",
              "state": {
                "query": "",
                "matchingCase": false,
                "explainSearch": false,
                "collapseAll": false,
                "extraContext": false,
                "sortOrder": "alphabetical"
              },
              "icon": "lucide-search",
              "title": "Search"
            }
          },
          {
            "id": "5aacc03d07e83851",
            "type": "leaf",
            "state": {
              "type": "bookmarks",
              "state": {},
              "icon": "lucide-bookmark",
              "title": "Bookmarks"
            }
          }
        ]
      }
    ],
    "direction": "horizontal",
    "width": 300
  },
  "right": {
    "id": "5cf8667944d911dd",
    "type": "split",
    "children": [
      {
        "id": "394ef4e894a74474",
        "type": "tabs",
        "children": [
          {
            "id": "2cb0fe19f88a6ec6",
            "type": "leaf",
            "state": {
              "type": "backlink",
              "state": {
                "file": "Installation.md",
                "collapseAll": false,
                "extraContext": false,
                "sortOrder": "alphabetical",
                "showSearch": false,
                "searchQuery": "",
                "backlinkCollapsed": false,
                "unlinkedCollapsed": true
              },
              "icon": "links-coming-in",
              "title": "Backlinks for Installation"
            }
          },
          {
            "id": "e8b794dddb9d59cb",
            "type": "leaf",
            "state": {
              "type": "outgoing-link",
              "state": {
                "file": "Installation.md",
                "linksCollapsed": false,
                "unlinkedCollapsed": true
              },
              "icon": "links-going-out",
              "title": "Outgoing links from Installation"
            }
          },
          {
            "id": "9c46dac682dbea08",
            "type": "leaf",
            "state": {
              "type": "tag",
              "state": {
                "sortOrder": "frequency",
                "useHierarchy": true,
                "showSearch": false,
                "searchQuery": ""
              },
              "icon": "lucide-tags",
              "title": "Tags"
            }
          },
          {
            "id": "3f27b517b9c62fd0",
            "type": "leaf",
            "state": {
              "type": "outline",
              "state": {
                "file": "Installation.md",
                "followCursor": false,
                "showSearch": false,
                "searchQuery": ""
              },
              "icon": "lucide-list",
              "title": "Outline of Installation"
            }
          }
        ]
      }
    ],
    "direction": "horizontal",
    "width": 300,
    "collapsed": true
  },
  "left-ribbon": {
    "hiddenItems": {
      "switcher:Open quick switcher": false,
      "graph:Open graph view": false,
      "canvas:Create new canvas": false,
      "daily-notes:Open today's daily note": false,
      "templates:Insert template": false,
      "command-palette:Open command palette": false
    }
  },
  "active": "735318b20f393cbb",
  "lastOpenFiles": [
    "Introduction.md",
    "Installation.md",
    "Images/Screenshot 2025-02-25 at 6.22.58 PM.png",
    "Images",
    "Images/Screenshot 2025-02-25 at 6.09.47 PM.png",
    "Untitled 1.md",
    "Untitled 2.md"
  ]
}